sphinx_feature_classification/__init__.py
sphinx_feature_classification/support-matrix.css
sphinx_feature_classification/support_matrix.py
sphinx_feature_classification/tests/__init__.py
sphinx_feature_classification/tests/base.py
sphinx_feature_classification/tests/test_sphinx_feature_classification.py
sphinx_feature_classification/tests/fakes/__init__.py
sphinx_feature_classification/tests/fakes/support-matrix.ini
sphinx_feature_classification-2.0.0.dist-info/AUTHORS
sphinx_feature_classification-2.0.0.dist-info/LICENSE
sphinx_feature_classification-2.0.0.dist-info/METADATA
sphinx_feature_classification-2.0.0.dist-info/WHEEL
sphinx_feature_classification-2.0.0.dist-info/pbr.json
sphinx_feature_classification-2.0.0.dist-info/top_level.txt
sphinx_feature_classification-2.0.0.dist-info/RECORD
